{
  "dominant_color": {
    "rgb": [
      44,
      30,
      68
    ],
    "hex": "#2c1e44"
  },
  "palette": [
    {
      "rgb": [
        44,
        30,
        68
      ],
      "hex": "#2c1e44"
    },
    {
      "rgb": [
        211,
        144,
        152
      ],
      "hex": "#d39098"
    },
    {
      "rgb": [
        70,
        189,
        239
      ],
      "hex": "#46bdef"
    },
    {
      "rgb": [
        118,
        112,
        219
      ],
      "hex": "#7670db"
    },
    {
      "rgb": [
        121,
        96,
        120
      ],
      "hex": "#796078"
    }
  ],
  "mood": "bold",
  "brightness": "dark"
}